AUTHORS.rst
CONTRIBUTING.md
HISTORY.rst
LICENSE
MANIFEST.in
README.rst
setup.cfg
setup.py
snorse.py
snorse.egg-info/PKG-INFO
snorse.egg-info/SOURCES.txt
snorse.egg-info/dependency_links.txt
snorse.egg-info/entry_points.txt
snorse.egg-info/not-zip-safe
snorse.egg-info/requires.txt
snorse.egg-info/top_level.txt
tests/__init__.py
tests/test_desnorse.py
tests/test_snorse.py