Metadata-Version: 1.1
Name: snorse
Version: 1.0.0
Summary: Unicode Snowman Morse Code
Home-page: https://github.com/pipermerriam/snorse
Author: Piper Merriam
Author-email: pipermerriam@gmail.com
License: MIT
Keywords: snorse
Platform: UNKNOWN
Classifier: Development Status :: 2 - Pre-Alpha
Classifier: Intended Audience :: Developers
Classifier: License :: OSI Approved :: BSD License
Classifier: Natural Language :: English
Classifier: Programming Language :: Python :: 2
Classifier: Programming Language :: Python :: 2.6
Classifier: Programming Language :: Python :: 2.7
Classifier: Programming Language :: Python :: 3
Classifier: Programming Language :: Python :: 3.3
Classifier: Programming Language :: Python :: 3.4
